ess/polarization/__init__.py
ess/polarization/base.py
ess/polarization/correction.py
ess/polarization/data.py
ess/polarization/he3.py
ess/polarization/py.typed
ess/polarization/supermirror.py
ess/polarization/types.py
ess/polarization/zoom.py
esspolarization-25.10.0.dist-info/licenses/LICENSE
esspolarization-25.10.0.dist-info/METADATA
esspolarization-25.10.0.dist-info/WHEEL
esspolarization-25.10.0.dist-info/top_level.txt
esspolarization-25.10.0.dist-info/RECORD
