Metadata-Version: 2.4
Name: esspolarization
Version: 25.10.0
Summary: Polarization data reduction for the European Spallation Source
Author: Scipp contributors
License-Expression: BSD-3-Clause
Project-URL: Bug Tracker, https://github.com/scipp/esspolarization/issues
Project-URL: Documentation, https://scipp.github.io/esspolarization
Project-URL: Source, https://github.com/scipp/esspolarization
Classifier: Intended Audience :: Science/Research
Classifier: Natural Language :: English
Classifier: Operating System :: OS Independent
Classifier: Programming Language :: Python :: 3
Classifier: Programming Language :: Python :: 3 :: Only
Classifier: Programming Language :: Python :: 3.11
Classifier: Programming Language :: Python :: 3.12
Classifier: Programming Language :: Python :: 3.13
Classifier: Topic :: Scientific/Engineering
Classifier: Typing :: Typed
Requires-Python: >=3.11
License-File: LICENSE
Requires-Dist: dask>=2022.1.0
Requires-Dist: graphviz
Requires-Dist: sciline>=25.04.1
Requires-Dist: scipp>=23.8.0
Requires-Dist: scipy>=1.14
Requires-Dist: essreduce>=24.07.1
Provides-Extra: test
Requires-Dist: pytest>=7.0; extra == "test"
Requires-Dist: pandas>=2.1.2; extra == "test"
Requires-Dist: pooch>=1.5; extra == "test"
Dynamic: license-file
